skelgen/__init__.py
skelgen/builder.py
skelgen/generator.py
skelgen/main.py
skelgen/parser.py
skelgen/utils.py
skelgen/templates/c/header_template.h.tpl
skelgen/templates/c/main_template.c.tpl
skelgen/templates/c/source_template.c.tpl
ez_skelgen-0.1.2.dist-info/METADATA
ez_skelgen-0.1.2.dist-info/WHEEL
ez_skelgen-0.1.2.dist-info/entry_points.txt
ez_skelgen-0.1.2.dist-info/top_level.txt
ez_skelgen-0.1.2.dist-info/RECORD
